contact_profiles_local/__init__.py
contact_profiles_local/contact_profiles_local.py
contact_profiles_local/contact_profiles_local_constants.py
contact_profiles_local-0.0.7.dist-info/METADATA
contact_profiles_local-0.0.7.dist-info/WHEEL
contact_profiles_local-0.0.7.dist-info/top_level.txt
contact_profiles_local-0.0.7.dist-info/RECORD
